blogit/__init__.py
blogit/_version.py
blogit/blogit.py
blogit/blogit-mir/README.md
blogit/blogit-mir/conf.py
blogit/blogit-mir/content/pages/about.md
blogit/blogit-mir/content/posts/1865-11-26-down-the-rabbit-hole.md
blogit/blogit-mir/content/posts/1871-03-18-looking-glass-house.md
blogit/blogit-mir/content/posts/1912-07-24-out-to-sea.md
blogit/blogit-mir/content/posts/1948-12-12-the-purpose-of-education.md
blogit/blogit-mir/content/posts/1963-08-28-i-have-a-dream.md
blogit/blogit-mir/content/posts/2014-08-12-the-businessman-and-fisherman.md
blogit/blogit-mir/media/css/bootstrap-theme.min.css
blogit/blogit-mir/media/css/bootstrap.min.css
blogit/blogit-mir/media/css/print.css
blogit/blogit-mir/media/css/pygments_style.css
blogit/blogit-mir/media/css/site.css
blogit/blogit-mir/media/css/style.css
blogit/blogit-mir/media/css/tipsy.css
blogit/blogit-mir/media/img/about.png
blogit/blogit-mir/media/img/body_bg.png
blogit/blogit-mir/media/img/code_top_bg.png
blogit/blogit-mir/media/img/flickr.png
blogit/blogit-mir/media/img/g+.png
blogit/blogit-mir/media/img/github.png
blogit/blogit-mir/media/img/home.png
blogit/blogit-mir/media/img/in.png
blogit/blogit-mir/media/img/noise.png
blogit/blogit-mir/media/img/rss.png
blogit/blogit-mir/media/img/twitter.png
blogit/blogit-mir/media/js/bootstrap.min.js
blogit/blogit-mir/media/js/googlefonts.js
blogit/blogit-mir/media/js/highlight.pack.js
blogit/blogit-mir/media/js/jquery.js
blogit/blogit-mir/media/js/jquery.min.js
blogit/blogit-mir/media/js/jquery.tipsy.js
blogit/blogit-mir/media/js/scripts.js
blogit/blogit-mir/templates/about.html
blogit/blogit-mir/templates/archive_index.html
blogit/blogit-mir/templates/atom.xml
blogit/blogit-mir/templates/base.html
blogit/blogit-mir/templates/discuss.html
blogit/blogit-mir/templates/entry.html
blogit/blogit-mir/templates/entry_index.html
blogit/blogit-mir/templates/explorer.html
blogit/blogit-mir/templates/google_analytics.html
blogit/blogit-mir/templates/sidebar.html
blogit-0.4.2.dist-info/AUTHORS
blogit-0.4.2.dist-info/LICENSE.txt
blogit-0.4.2.dist-info/METADATA
blogit-0.4.2.dist-info/NOTICE.txt
blogit-0.4.2.dist-info/WHEEL
blogit-0.4.2.dist-info/entry_points.txt
blogit-0.4.2.dist-info/top_level.txt
blogit-0.4.2.dist-info/RECORD
