Metadata-Version: 2.1
Name: blogit
Version: 0.4.2
Author-email: Oz N Tiram <oz.tiram@gmail.com>
Project-URL: homepage, https://gitlab.com/oz123/blogit
Classifier: Development Status :: 3 - Alpha
Classifier: Programming Language :: Python
Classifier: Programming Language :: Python :: 3.9
Classifier: Programming Language :: Python :: 3.10
Classifier: Programming Language :: Python :: 3.11
Classifier: Intended Audience :: System Administrators
Classifier: Environment :: Console
Classifier: Environment :: Web Environment
Classifier: Intended Audience :: End Users/Desktop
Classifier: Intended Audience :: Developers
Classifier: License :: OSI Approved :: GNU General Public License v3 or later (GPLv3+)
Classifier: Intended Audience :: Developers
Classifier: Operating System :: OS Independent
Classifier: Topic :: Software Development
License-File: LICENSE.txt
License-File: NOTICE.txt
License-File: AUTHORS
Requires-Dist: markdown2 >=2.3.2
Requires-Dist: tinydb >=3.6.0
Requires-Dist: jinja2
Requires-Dist: pygments
